<annotation>
	<folder>RSData</folder>
	<filename>Result_197.jpg</filename>
	<source>
		<database>HSRI-OBJDET</database>
	</source>
	<size>
		<width>4096</width>
		<height>4096</height>
		<depth>3</depth>
	</size>
	<segmented>0</segmented>
	<object>
		<name>«≈¡∫</name>
		<pose>Unspecified</pose>
		<truncated>0</truncated>
		<difficult>0</difficult>
		<bndbox>
			<xmin>153</xmin>
			<ymin>3896</ymin>
			<xmax>224</xmax>
			<ymax>3983</ymax>
		</bndbox>
	</object>
	<object>
		<name>«≈¡∫</name>
		<pose>Unspecified</pose>
		<truncated>0</truncated>
		<difficult>0</difficult>
		<bndbox>
			<xmin>746</xmin>
			<ymin>3797</ymin>
			<xmax>810</xmax>
			<ymax>3813</ymax>
		</bndbox>
	</object>
	<object>
		<name>«≈¡∫</name>
		<pose>Unspecified</pose>
		<truncated>0</truncated>
		<difficult>0</difficult>
		<bndbox>
			<xmin>742</xmin>
			<ymin>3831</ymin>
			<xmax>802</xmax>
			<ymax>3853</ymax>
		</bndbox>
	</object>
	<object>
		<name>«≈¡∫</name>
		<pose>Unspecified</pose>
		<truncated>0</truncated>
		<difficult>0</difficult>
		<bndbox>
			<xmin>2903</xmin>
			<ymin>3313</ymin>
			<xmax>2968</xmax>
			<ymax>3349</ymax>
		</bndbox>
	</object>
	<object>
		<name>«≈¡∫</name>
		<pose>Unspecified</pose>
		<truncated>0</truncated>
		<difficult>0</difficult>
		<bndbox>
			<xmin>2715</xmin>
			<ymin>2404</ymin>
			<xmax>2884</xmax>
			<ymax>2427</ymax>
		</bndbox>
	</object>
	<object>
		<name>«≈¡∫</name>
		<pose>Unspecified</pose>
		<truncated>0</truncated>
		<difficult>0</difficult>
		<bndbox>
			<xmin>2714</xmin>
			<ymin>2428</ymin>
			<xmax>2886</xmax>
			<ymax>2446</ymax>
		</bndbox>
	</object>
	<object>
		<name>«≈¡∫</name>
		<pose>Unspecified</pose>
		<truncated>0</truncated>
		<difficult>0</difficult>
		<bndbox>
			<xmin>2182</xmin>
			<ymin>2174</ymin>
			<xmax>2213</xmax>
			<ymax>2203</ymax>
		</bndbox>
	</object>
	<object>
		<name>«≈¡∫</name>
		<pose>Unspecified</pose>
		<truncated>0</truncated>
		<difficult>0</difficult>
		<bndbox>
			<xmin>2162</xmin>
			<ymin>2187</ymin>
			<xmax>2194</xmax>
			<ymax>2216</ymax>
		</bndbox>
	</object>
	<object>
		<name>«≈¡∫</name>
		<pose>Unspecified</pose>
		<truncated>0</truncated>
		<difficult>0</difficult>
		<bndbox>
			<xmin>2384</xmin>
			<ymin>427</ymin>
			<xmax>2429</xmax>
			<ymax>472</ymax>
		</bndbox>
	</object>
	<object>
		<name>«≈¡∫</name>
		<pose>Unspecified</pose>
		<truncated>0</truncated>
		<difficult>0</difficult>
		<bndbox>
			<xmin>2429</xmin>
			<ymin>556</ymin>
			<xmax>2481</xmax>
			<ymax>595</ymax>
		</bndbox>
	</object>
	<object>
		<name>«≈¡∫</name>
		<pose>Unspecified</pose>
		<truncated>0</truncated>
		<difficult>0</difficult>
		<bndbox>
			<xmin>112</xmin>
			<ymin>3834</ymin>
			<xmax>144</xmax>
			<ymax>3864</ymax>
		</bndbox>
	</object>
</annotation>