<annotation>
	<folder>RSData</folder>
	<filename>Result_119.jpg</filename>
	<source>
		<database>HSRI-OBJDET</database>
	</source>
	<size>
		<width>4096</width>
		<height>4096</height>
		<depth>3</depth>
	</size>
	<segmented>0</segmented>
	<object>
		<name>´¬Ö»</name>
		<pose>Unspecified</pose>
		<truncated>0</truncated>
		<difficult>0</difficult>
		<bndbox>
			<xmin>643</xmin>
			<ymin>2566</ymin>
			<xmax>779</xmax>
			<ymax>2730</ymax>
		</bndbox>
	</object>
</annotation>