<annotation>
	<folder>RSData</folder>
	<filename>Result_177.jpg</filename>
	<source>
		<database>HSRI-OBJDET</database>
	</source>
	<size>
		<width>4096</width>
		<height>4096</height>
		<depth>3</depth>
	</size>
	<segmented>0</segmented>
	<object>
		<name>¬ÎÕ∑</name>
		<pose>Unspecified</pose>
		<truncated>0</truncated>
		<difficult>0</difficult>
		<bndbox>
			<xmin>2303</xmin>
			<ymin>3787</ymin>
			<xmax>3034</xmax>
			<ymax>4095</ymax>
		</bndbox>
	</object>
	<object>
		<name>«≈¡∫</name>
		<pose>Unspecified</pose>
		<truncated>0</truncated>
		<difficult>0</difficult>
		<bndbox>
			<xmin>3333</xmin>
			<ymin>4027</ymin>
			<xmax>3365</xmax>
			<ymax>4049</ymax>
		</bndbox>
	</object>
	<object>
		<name>«≈¡∫</name>
		<pose>Unspecified</pose>
		<truncated>0</truncated>
		<difficult>0</difficult>
		<bndbox>
			<xmin>3730</xmin>
			<ymin>4028</ymin>
			<xmax>3762</xmax>
			<ymax>4061</ymax>
		</bndbox>
	</object>
</annotation>