<annotation>
	<folder>RSData</folder>
	<filename>Result_228.jpg</filename>
	<source>
		<database>HSRI-OBJDET</database>
	</source>
	<size>
		<width>4096</width>
		<height>4096</height>
		<depth>3</depth>
	</size>
	<segmented>0</segmented>
	<object>
		<name>¬ÎÕ∑</name>
		<pose>Unspecified</pose>
		<truncated>0</truncated>
		<difficult>0</difficult>
		<bndbox>
			<xmin>1145</xmin>
			<ymin>1828</ymin>
			<xmax>1434</xmax>
			<ymax>2027</ymax>
		</bndbox>
	</object>
	<object>
		<name>¬ÎÕ∑</name>
		<pose>Unspecified</pose>
		<truncated>0</truncated>
		<difficult>0</difficult>
		<bndbox>
			<xmin>4</xmin>
			<ymin>847</ymin>
			<xmax>513</xmax>
			<ymax>1428</ymax>
		</bndbox>
	</object>
	<object>
		<name>¥¨÷ª</name>
		<pose>Unspecified</pose>
		<truncated>0</truncated>
		<difficult>0</difficult>
		<bndbox>
			<xmin>1363</xmin>
			<ymin>1802</ymin>
			<xmax>1419</xmax>
			<ymax>1844</ymax>
		</bndbox>
	</object>
	<object>
		<name>«≈¡∫</name>
		<pose>Unspecified</pose>
		<truncated>0</truncated>
		<difficult>0</difficult>
		<bndbox>
			<xmin>2540</xmin>
			<ymin>2457</ymin>
			<xmax>2567</xmax>
			<ymax>2497</ymax>
		</bndbox>
	</object>
	<object>
		<name>«≈¡∫</name>
		<pose>Unspecified</pose>
		<truncated>0</truncated>
		<difficult>0</difficult>
		<bndbox>
			<xmin>421</xmin>
			<ymin>4039</ymin>
			<xmax>490</xmax>
			<ymax>4096</ymax>
		</bndbox>
	</object>
	<object>
		<name>«≈¡∫</name>
		<pose>Unspecified</pose>
		<truncated>0</truncated>
		<difficult>0</difficult>
		<bndbox>
			<xmin>1406</xmin>
			<ymin>3575</ymin>
			<xmax>1445</xmax>
			<ymax>3642</ymax>
		</bndbox>
	</object>
	<object>
		<name>«≈¡∫</name>
		<pose>Unspecified</pose>
		<truncated>0</truncated>
		<difficult>0</difficult>
		<bndbox>
			<xmin>1731</xmin>
			<ymin>3491</ymin>
			<xmax>1787</xmax>
			<ymax>3533</ymax>
		</bndbox>
	</object>
	<object>
		<name>«≈¡∫</name>
		<pose>Unspecified</pose>
		<truncated>0</truncated>
		<difficult>0</difficult>
		<bndbox>
			<xmin>1917</xmin>
			<ymin>3423</ymin>
			<xmax>1974</xmax>
			<ymax>3462</ymax>
		</bndbox>
	</object>
	<object>
		<name>≤Ÿ≥°</name>
		<pose>Unspecified</pose>
		<truncated>0</truncated>
		<difficult>0</difficult>
		<bndbox>
			<xmin>3948</xmin>
			<ymin>2485</ymin>
			<xmax>4079</xmax>
			<ymax>2661</ymax>
		</bndbox>
	</object>
	<object>
		<name>«≈¡∫</name>
		<pose>Unspecified</pose>
		<truncated>0</truncated>
		<difficult>0</difficult>
		<bndbox>
			<xmin>3961</xmin>
			<ymin>2426</ymin>
			<xmax>3990</xmax>
			<ymax>2475</ymax>
		</bndbox>
	</object>
	<object>
		<name>«≈¡∫</name>
		<pose>Unspecified</pose>
		<truncated>0</truncated>
		<difficult>0</difficult>
		<bndbox>
			<xmin>3571</xmin>
			<ymin>2480</ymin>
			<xmax>3597</xmax>
			<ymax>2525</ymax>
		</bndbox>
	</object>
	<object>
		<name>«≈¡∫</name>
		<pose>Unspecified</pose>
		<truncated>0</truncated>
		<difficult>0</difficult>
		<bndbox>
			<xmin>3812</xmin>
			<ymin>2458</ymin>
			<xmax>3846</xmax>
			<ymax>2522</ymax>
		</bndbox>
	</object>
	<object>
		<name>¬ÎÕ∑</name>
		<pose>Unspecified</pose>
		<truncated>0</truncated>
		<difficult>0</difficult>
		<bndbox>
			<xmin>3189</xmin>
			<ymin>3693</ymin>
			<xmax>3664</xmax>
			<ymax>4095</ymax>
		</bndbox>
	</object>
</annotation>