<annotation>
	<folder>RSData</folder>
	<filename>Result_180.jpg</filename>
	<source>
		<database>HSRI-OBJDET</database>
	</source>
	<size>
		<width>4096</width>
		<height>4096</height>
		<depth>3</depth>
	</size>
	<segmented>0</segmented>
	<object>
		<name>飞机</name>
		<pose>Unspecified</pose>
		<truncated>0</truncated>
		<difficult>0</difficult>
		<bndbox>
			<xmin>3231</xmin>
			<ymin>1478</ymin>
			<xmax>3275</xmax>
			<ymax>1516</ymax>
		</bndbox>
	</object>
	<object>
		<name>飞机</name>
		<pose>Unspecified</pose>
		<truncated>0</truncated>
		<difficult>0</difficult>
		<bndbox>
			<xmin>3162</xmin>
			<ymin>1485</ymin>
			<xmax>3210</xmax>
			<ymax>1518</ymax>
		</bndbox>
	</object>
	<object>
		<name>飞机</name>
		<pose>Unspecified</pose>
		<truncated>0</truncated>
		<difficult>0</difficult>
		<bndbox>
			<xmin>3175</xmin>
			<ymin>1417</ymin>
			<xmax>3222</xmax>
			<ymax>1451</ymax>
		</bndbox>
	</object>
	<object>
		<name>飞机</name>
		<pose>Unspecified</pose>
		<truncated>0</truncated>
		<difficult>0</difficult>
		<bndbox>
			<xmin>3102</xmin>
			<ymin>1400</ymin>
			<xmax>3126</xmax>
			<ymax>1419</ymax>
		</bndbox>
	</object>
	<object>
		<name>飞机</name>
		<pose>Unspecified</pose>
		<truncated>0</truncated>
		<difficult>0</difficult>
		<bndbox>
			<xmin>2859</xmin>
			<ymin>318</ymin>
			<xmax>2897</xmax>
			<ymax>351</ymax>
		</bndbox>
	</object>
	<object>
		<name>飞机</name>
		<pose>Unspecified</pose>
		<truncated>0</truncated>
		<difficult>0</difficult>
		<bndbox>
			<xmin>1861</xmin>
			<ymin>798</ymin>
			<xmax>1916</xmax>
			<ymax>833</ymax>
		</bndbox>
	</object>
	<object>
		<name>飞机</name>
		<pose>Unspecified</pose>
		<truncated>0</truncated>
		<difficult>0</difficult>
		<bndbox>
			<xmin>1764</xmin>
			<ymin>594</ymin>
			<xmax>1834</xmax>
			<ymax>651</ymax>
		</bndbox>
	</object>
	<object>
		<name>飞机</name>
		<pose>Unspecified</pose>
		<truncated>0</truncated>
		<difficult>0</difficult>
		<bndbox>
			<xmin>1941</xmin>
			<ymin>474</ymin>
			<xmax>2012</xmax>
			<ymax>536</ymax>
		</bndbox>
	</object>
	<object>
		<name>飞机</name>
		<pose>Unspecified</pose>
		<truncated>0</truncated>
		<difficult>0</difficult>
		<bndbox>
			<xmin>1730</xmin>
			<ymin>435</ymin>
			<xmax>1794</xmax>
			<ymax>490</ymax>
		</bndbox>
	</object>
	<object>
		<name>飞机</name>
		<pose>Unspecified</pose>
		<truncated>0</truncated>
		<difficult>0</difficult>
		<bndbox>
			<xmin>1684</xmin>
			<ymin>267</ymin>
			<xmax>1753</xmax>
			<ymax>325</ymax>
		</bndbox>
	</object>
	<object>
		<name>飞机</name>
		<pose>Unspecified</pose>
		<truncated>0</truncated>
		<difficult>0</difficult>
		<bndbox>
			<xmin>2482</xmin>
			<ymin>577</ymin>
			<xmax>2521</xmax>
			<ymax>619</ymax>
		</bndbox>
	</object>
	<object>
		<name>飞机</name>
		<pose>Unspecified</pose>
		<truncated>0</truncated>
		<difficult>0</difficult>
		<bndbox>
			<xmin>3274</xmin>
			<ymin>1121</ymin>
			<xmax>3308</xmax>
			<ymax>1161</ymax>
		</bndbox>
	</object>
	<object>
		<name>飞机</name>
		<pose>Unspecified</pose>
		<truncated>0</truncated>
		<difficult>0</difficult>
		<bndbox>
			<xmin>2881</xmin>
			<ymin>3652</ymin>
			<xmax>2929</xmax>
			<ymax>3698</ymax>
		</bndbox>
	</object>
	<object>
		<name>船只</name>
		<pose>Unspecified</pose>
		<truncated>0</truncated>
		<difficult>0</difficult>
		<bndbox>
			<xmin>3973</xmin>
			<ymin>742</ymin>
			<xmax>4041</xmax>
			<ymax>890</ymax>
		</bndbox>
	</object>
	<object>
		<name>码头</name>
		<pose>Unspecified</pose>
		<truncated>0</truncated>
		<difficult>0</difficult>
		<bndbox>
			<xmin>3901</xmin>
			<ymin>349</ymin>
			<xmax>4093</xmax>
			<ymax>1086</ymax>
		</bndbox>
	</object>
</annotation>