<annotation>
	<folder>RSData</folder>
	<filename>Result_230.jpg</filename>
	<source>
		<database>HSRI-OBJDET</database>
	</source>
	<size>
		<width>4096</width>
		<height>4096</height>
		<depth>3</depth>
	</size>
	<segmented>0</segmented>
	<object>
		<name>²Ù³¡</name>
		<pose>Unspecified</pose>
		<truncated>0</truncated>
		<difficult>0</difficult>
		<bndbox>
			<xmin>2765</xmin>
			<ymin>1454</ymin>
			<xmax>2904</xmax>
			<ymax>1645</ymax>
		</bndbox>
	</object>
	<object>
		<name>²Ù³¡</name>
		<pose>Unspecified</pose>
		<truncated>0</truncated>
		<difficult>0</difficult>
		<bndbox>
			<xmin>2512</xmin>
			<ymin>196</ymin>
			<xmax>2622</xmax>
			<ymax>328</ymax>
		</bndbox>
	</object>
	<object>
		<name>ÂëÍ·</name>
		<pose>Unspecified</pose>
		<truncated>0</truncated>
		<difficult>0</difficult>
		<bndbox>
			<xmin>486</xmin>
			<ymin>181</ymin>
			<xmax>1023</xmax>
			<ymax>535</ymax>
		</bndbox>
	</object>
</annotation>